{"assets":{"351367B6BFF2D0A8C3AE0D97030CD1F4":{"type":"texture","index":0,"url":{"native":"assets\/5C893BFB-55DE-4CF8-925C-2B98D2D0D201.pdf"},"width":1280,"height":720},"8EF0FA623127CAE4A8779811A112E284":{"type":"texture","index":1,"url":{"native":"assets\/5C893BFB-55DE-4CF8-925C-2B98D2D0D201.pdf"},"width":1280,"height":720}},"events":[{"effects":[{"beginTime":0,"baseLayer":{"animations":[],"initialState":{"affineTransform":[1,0,0,1,0,0],"masksToBounds":false,"rotation":0,"scale":1,"position":{"pointX":640,"pointY":360},"width":1280,"sublayerTransform":[1,0,0,0,0,1,0,0,0,0,1,0,0,0,0,1],"contentsRect":{"y":0,"x":0,"width":1,"height":1},"opacity":1,"edgeAntialiasingMask":251658240,"height":720,"hidden":false,"anchorPoint":{"pointX":0.5,"pointY":0.5}},"objectID":"0","layers":[{"animations":[],"initialState":{"affineTransform":[1,0,0,1,0,0],"masksToBounds":false,"rotation":0,"scale":1,"position":{"pointX":640,"pointY":360},"width":1280,"sublayerTransform":[1,0,0,0,0,1,0,0,0,0,1,-0.0005251186870016398,0,0,0,1],"contentsRect":{"y":0,"x":0,"width":1,"height":1},"opacity":1,"edgeAntialiasingMask":251658240,"height":720,"hidden":false,"anchorPoint":{"pointX":0.5,"pointY":0.5}},"layers":[{"animations":[],"layers":[],"texturedRectangle":{"isBackgroundTexture":false,"singleTextureOpacity":1,"textureType":0,"textBaseline":0,"textXHeight":0,"isVerticalText":false},"initialState":{"affineTransform":[1,0,0,1,0,0],"masksToBounds":false,"rotation":0,"scale":1,"position":{"pointX":640,"pointY":360},"width":1280,"sublayerTransform":[1,0,0,0,0,1,0,0,0,0,1,0,0,0,0,1],"contentsRect":{"y":0,"x":0,"width":1,"height":1},"opacity":1,"edgeAntialiasingMask":0,"height":720,"hidden":false,"anchorPoint":{"pointX":0.5,"pointY":0.5}},"texture":"8EF0FA623127CAE4A8779811A112E284"},{"animations":[{"additive":false,"timeOffset":0,"beginTime":0,"from":{"scalar":false},"repeatCount":0,"fillMode":"both","duration":0.01,"autoreverses":false,"property":"hidden","to":{"scalar":true},"removedOnCompletion":false}],"layers":[],"texturedRectangle":{"isBackgroundTexture":false,"singleTextureOpacity":1,"textureType":0,"textBaseline":0,"textXHeight":0,"isVerticalText":false},"initialState":{"affineTransform":[1,0,0,1,0,0],"masksToBounds":false,"rotation":0,"scale":1,"position":{"pointX":640,"pointY":360},"width":1280,"sublayerTransform":[1,0,0,0,0,1,0,0,0,0,1,0,0,0,0,1],"contentsRect":{"y":0,"x":0,"width":1,"height":1},"opacity":1,"edgeAntialiasingMask":0,"height":720,"hidden":false,"anchorPoint":{"pointX":0.5,"pointY":0.5}},"texture":"351367B6BFF2D0A8C3AE0D97030CD1F4"}]}]},"effects":[],"duration":0.01,"type":"transition","attributes":{"direction":0},"name":"none","objectID":"0"}],"automaticPlay":false,"hyperlinks":[],"accessibility":[{"text":"￼","targetRectangle":{"y":687,"x":627.99999934434891,"width":24,"height":19}},{"text":"Text","targetRectangle":{"y":472,"x":211.5,"width":67.1123046875,"height":44}},{"text":"Cc","targetRectangle":{"y":40,"x":559.93788146972656,"width":210.24000000000001,"height":144}},{"text":"Aa","targetRectangle":{"y":35,"x":44.600967407226562,"width":204.91199999999998,"height":144}},{"text":"Bb","targetRectangle":{"y":305,"x":302.62549591064453,"width":180.86399999999998,"height":144}},{"text":"Ee","targetRectangle":{"y":26,"x":1041.664924621582,"width":170.78400000000011,"height":144}},{"text":"Dd","targetRectangle":{"y":26,"x":806.16920471191406,"width":205.77599999999995,"height":144}},{"text":"Text","targetRectangle":{"y":338,"x":203.5,"width":67.1123046875,"height":44}}],"baseLayer":{"animations":[],"initialState":{"affineTransform":[1,0,0,1,0,0],"masksToBounds":false,"rotation":0,"scale":1,"position":{"pointX":640,"pointY":360},"width":1280,"sublayerTransform":[1,0,0,0,0,1,0,0,0,0,1,0,0,0,0,1],"contentsRect":{"y":0,"x":0,"width":1,"height":1},"opacity":1,"edgeAntialiasingMask":251658240,"height":720,"hidden":false,"anchorPoint":{"pointX":0.5,"pointY":0.5}},"objectID":"0","layers":[{"animations":[],"initialState":{"affineTransform":[1,0,0,1,0,0],"masksToBounds":false,"rotation":0,"scale":1,"position":{"pointX":640,"pointY":360},"width":1280,"sublayerTransform":[1,0,0,0,0,1,0,0,0,0,1,-0.0005251186870016398,0,0,0,1],"contentsRect":{"y":0,"x":0,"width":1,"height":1},"opacity":1,"edgeAntialiasingMask":251658240,"height":720,"hidden":false,"anchorPoint":{"pointX":0.5,"pointY":0.5}},"layers":[{"animations":[],"layers":[],"texturedRectangle":{"isBackgroundTexture":false,"singleTextureOpacity":1,"textureType":0,"textBaseline":0,"textXHeight":0,"isVerticalText":false},"initialState":{"affineTransform":[1,0,0,1,0,0],"masksToBounds":false,"rotation":0,"scale":1,"position":{"pointX":640,"pointY":360},"width":1280,"sublayerTransform":[1,0,0,0,0,1,0,0,0,0,1,0,0,0,0,1],"contentsRect":{"y":0,"x":0,"width":1,"height":1},"opacity":1,"edgeAntialiasingMask":0,"height":720,"hidden":false,"anchorPoint":{"pointX":0.5,"pointY":0.5}},"texture":"351367B6BFF2D0A8C3AE0D97030CD1F4"}]}]}}]}