{"assets":{"453908F53C17B73A863A51D614A958E3":{"type":"texture","index":9,"url":{"native":"assets\/811105C6-9793-4984-A325-39E4853439BD.pdf"},"width":224,"height":229},"5840FDD888AEFE7FEE4D3E821FDD3156":{"type":"texture","index":4,"url":{"native":"assets\/811105C6-9793-4984-A325-39E4853439BD.pdf"},"width":27,"height":14},"9B0CE0A95728ED838AEA01C26CB7FA57":{"type":"texture","index":6,"url":{"native":"assets\/811105C6-9793-4984-A325-39E4853439BD.pdf"},"width":224,"height":229},"C30918506A3DD362A001CD80A988B4D7":{"type":"texture","index":3,"url":{"native":"assets\/811105C6-9793-4984-A325-39E4853439BD.pdf"},"width":304,"height":209},"2F02F0C77F8F15244453071F240333F3":{"type":"texture","index":0,"url":{"native":"assets\/811105C6-9793-4984-A325-39E4853439BD.pdf"},"width":1280,"height":720},"2CACF84A11B392050CFF2F099D092F82":{"type":"texture","index":8,"url":{"native":"assets\/811105C6-9793-4984-A325-39E4853439BD.pdf"},"width":27,"height":14},"1347933E04244CB1F684C3CBCC629084":{"type":"texture","index":1,"url":{"native":"assets\/811105C6-9793-4984-A325-39E4853439BD.pdf"},"width":553,"height":144},"A8288665C890835D50CBD17E8C8FEB9D":{"type":"texture","index":7,"url":{"native":"assets\/811105C6-9793-4984-A325-39E4853439BD.pdf"},"width":380,"height":209},"4A1483485811F20AF8B070A742C121A3":{"type":"texture","index":5,"url":{"native":"assets\/811105C6-9793-4984-A325-39E4853439BD.pdf"},"width":345,"height":211},"F5118637D28E65DB0CFE82C14CCECE8E":{"type":"texture","index":2,"url":{"native":"assets\/811105C6-9793-4984-A325-39E4853439BD.pdf"},"width":357,"height":357}},"events":[{"effects":[{"beginTime":0.5,"baseLayer":{"animations":[],"initialState":{"affineTransform":[1,0,0,1,0,0],"masksToBounds":false,"rotation":0,"scale":1,"position":{"pointX":350.5,"pointY":504.152587890625},"width":357,"sublayerTransform":[1,0,0,0,0,1,0,0,0,0,1,0,0,0,0,1],"contentsRect":{"y":0,"x":0,"width":1,"height":1},"opacity":1,"edgeAntialiasingMask":251658240,"height":357,"hidden":false,"anchorPoint":{"pointX":0.5,"pointY":0.5}},"objectID":"FBE84E8B-A122-4C17-816E-B2840CD504E5","layers":[{"animations":[],"initialState":{"affineTransform":[1,0,0,1,0,0],"masksToBounds":false,"rotation":0,"scale":1,"position":{"pointX":468,"pointY":34.347412109375},"width":357,"sublayerTransform":[1,0,0,0,0,1,0,0,0,0,1,-0.0005251186870016398,0,0,0,1],"contentsRect":{"y":0,"x":0,"width":1,"height":1},"opacity":1,"edgeAntialiasingMask":251658240,"height":357,"hidden":false,"anchorPoint":{"pointX":1.3109243697478992,"pointY":0.096211238401610638}},"layers":[{"animations":[{"additive":false,"timeOffset":0,"beginTime":0.5,"repeatCount":0,"fillMode":"both","duration":1,"autoreverses":false,"animations":[{"repeatCount":0,"removedOnCompletion":true,"from":{"scalar":0},"timingFunction":"EaseInEaseOut","additive":false,"timeOffset":0,"autoreverses":false,"property":"opacity","fillMode":"both","duration":1,"beginTime":0,"to":{"scalar":1}},{"repeatCount":0,"removedOnCompletion":true,"timingFunctions":[{"timingFunction":"custom","timingControlPoint1y":0.19118130207061768,"timingControlPoint2x":1,"timingControlPoint1x":0.9568135142326355,"timingControlPoint2y":1},{"timingFunction":"custom","timingControlPoint1y":0,"timingControlPoint2x":0.50195950269699097,"timingControlPoint1x":0,"timingControlPoint2y":0.68968570232391357},{"timingFunction":"custom","timingControlPoint1y":0.10000000149011612,"timingControlPoint2x":1,"timingControlPoint1x":0.25,"timingControlPoint2y":1}],"keyTimes":[0,0.84999999999999998,0.94999999999999996,1],"additive":false,"values":[{"scalar":0.001},{"scalar":1.125},{"scalar":0.95199999999999996},{"scalar":0.99999999999999989}],"timeOffset":0,"autoreverses":false,"property":"transform.scale.xy","fillMode":"removed","duration":1,"beginTime":0},{"additive":false,"timeOffset":0,"beginTime":0.0001,"from":{"scalar":false},"repeatCount":0,"fillMode":"forwards","duration":0.99990000000000001,"autoreverses":false,"property":"hidden","to":{"scalar":false},"removedOnCompletion":true}],"removedOnCompletion":false}],"layers":[],"texturedRectangle":{"isBackgroundTexture":true,"singleTextureOpacity":1,"textureType":5,"textBaseline":0,"textXHeight":0,"isVerticalText":false},"initialState":{"affineTransform":[1,0,0,1,0,0],"masksToBounds":false,"rotation":0,"scale":1,"position":{"pointX":177.5,"pointY":176.847412109375},"width":357,"sublayerTransform":[1,0,0,0,0,1,0,0,0,0,1,0,0,0,0,1],"contentsRect":{"y":0,"x":0,"width":1,"height":1},"opacity":1,"edgeAntialiasingMask":0,"height":357,"hidden":true,"anchorPoint":{"pointX":0.5,"pointY":0.5}},"texture":"F5118637D28E65DB0CFE82C14CCECE8E"}]}]},"effects":[],"duration":1,"type":"buildIn","attributes":{"direction":0},"name":"apple:pop","objectID":"FBE84E8B-A122-4C17-816E-B2840CD504E5"},{"beginTime":0.5,"baseLayer":{"animations":[],"initialState":{"affineTransform":[1,0,0,1,0,0],"masksToBounds":false,"rotation":0,"scale":1,"position":{"pointX":797.0147705078125,"pointY":117},"width":553,"sublayerTransform":[1,0,0,0,0,1,0,0,0,0,1,0,0,0,0,1],"contentsRect":{"y":0,"x":0,"width":1,"height":1},"opacity":1,"edgeAntialiasingMask":251658240,"height":144,"hidden":false,"anchorPoint":{"pointX":0.5,"pointY":0.5}},"objectID":"FB3377F4-D05D-46FE-B488-6DE00A805E0D","layers":[{"animations":[],"initialState":{"affineTransform":[1,0,0,1,0,0],"masksToBounds":false,"rotation":0,"scale":1,"position":{"pointX":119.4852294921875,"pointY":315},"width":553,"sublayerTransform":[1,0,0,0,0,1,0,0,0,0,1,-0.0005251186870016398,0,0,0,1],"contentsRect":{"y":0,"x":0,"width":1,"height":1},"opacity":1,"edgeAntialiasingMask":251658240,"height":144,"hidden":false,"anchorPoint":{"pointX":0.21606732277068263,"pointY":2.1875}},"layers":[{"animations":[{"additive":false,"timeOffset":0,"beginTime":0.5,"repeatCount":0,"fillMode":"both","duration":1,"autoreverses":false,"animations":[{"repeatCount":0,"removedOnCompletion":true,"from":{"scalar":0},"timingFunction":"EaseInEaseOut","additive":false,"timeOffset":0,"autoreverses":false,"property":"opacity","fillMode":"both","duration":1,"beginTime":0,"to":{"scalar":1}},{"repeatCount":0,"removedOnCompletion":true,"timingFunctions":[{"timingFunction":"custom","timingControlPoint1y":0.19118130207061768,"timingControlPoint2x":1,"timingControlPoint1x":0.9568135142326355,"timingControlPoint2y":1},{"timingFunction":"custom","timingControlPoint1y":0,"timingControlPoint2x":0.50195950269699097,"timingControlPoint1x":0,"timingControlPoint2y":0.68968570232391357},{"timingFunction":"custom","timingControlPoint1y":0.10000000149011612,"timingControlPoint2x":1,"timingControlPoint1x":0.25,"timingControlPoint2y":1}],"keyTimes":[0,0.84999999999999998,0.94999999999999996,1],"additive":false,"values":[{"scalar":0.001},{"scalar":1.125},{"scalar":0.95199999999999996},{"scalar":0.99999999999999989}],"timeOffset":0,"autoreverses":false,"property":"transform.scale.xy","fillMode":"removed","duration":1,"beginTime":0},{"additive":false,"timeOffset":0,"beginTime":0.0001,"from":{"scalar":false},"repeatCount":0,"fillMode":"forwards","duration":0.99990000000000001,"autoreverses":false,"property":"hidden","to":{"scalar":false},"removedOnCompletion":true}],"removedOnCompletion":false}],"layers":[],"texturedRectangle":{"singleTextureOpacity":1,"textXHeight":1.0260416666666667,"textBaseline":1.0625010596381292,"isBackgroundTexture":true,"isVerticalText":false,"textColor":[0,0,0,1],"textureType":6},"initialState":{"affineTransform":[1,0,0,1,0,0],"masksToBounds":false,"rotation":0,"scale":1,"position":{"pointX":304.9852294921875,"pointY":138},"width":553,"sublayerTransform":[1,0,0,0,0,1,0,0,0,0,1,0,0,0,0,1],"contentsRect":{"y":0,"x":0,"width":1,"height":1},"opacity":1,"edgeAntialiasingMask":0,"height":144,"hidden":true,"anchorPoint":{"pointX":0.5,"pointY":0.5}},"texture":"1347933E04244CB1F684C3CBCC629084"}]}]},"effects":[{"beginTime":0,"baseLayer":{"animations":[],"initialState":{"affineTransform":[1,0,0,1,0,0],"masksToBounds":false,"rotation":0,"scale":1,"position":{"pointX":812.64599609375,"pointY":479.5},"width":345,"sublayerTransform":[1,0,0,0,0,1,0,0,0,0,1,0,0,0,0,1],"contentsRect":{"y":0,"x":0,"width":1,"height":1},"opacity":1,"edgeAntialiasingMask":251658240,"height":211,"hidden":false,"anchorPoint":{"pointX":0.5,"pointY":0.5}},"objectID":"5009FB8B-8410-482E-9042-03C87056AD2D","layers":[{"animations":[],"initialState":{"affineTransform":[1,0,0,1,0,0],"masksToBounds":false,"rotation":0,"scale":1,"position":{"pointX":-0.14599609375,"pointY":-14},"width":345,"sublayerTransform":[1,0,0,0,0,1,0,0,0,0,1,-0.0005251186870016398,0,0,0,1],"contentsRect":{"y":0,"x":0,"width":1,"height":1},"opacity":1,"edgeAntialiasingMask":251658240,"height":211,"hidden":false,"anchorPoint":{"pointX":-0.00042317708333333335,"pointY":-0.066350710900473939}},"layers":[{"animations":[{"additive":false,"timeOffset":0,"beginTime":1e-100,"repeatCount":0,"fillMode":"both","duration":1,"autoreverses":false,"animations":[{"repeatCount":0,"removedOnCompletion":true,"from":{"scalar":0},"timingFunction":"EaseInEaseOut","additive":false,"timeOffset":0,"autoreverses":false,"property":"opacity","fillMode":"both","duration":1,"beginTime":0,"to":{"scalar":1}},{"repeatCount":0,"removedOnCompletion":true,"timingFunctions":[{"timingFunction":"custom","timingControlPoint1y":0.19118130207061768,"timingControlPoint2x":1,"timingControlPoint1x":0.9568135142326355,"timingControlPoint2y":1},{"timingFunction":"custom","timingControlPoint1y":0,"timingControlPoint2x":0.50195950269699097,"timingControlPoint1x":0,"timingControlPoint2y":0.68968570232391357},{"timingFunction":"custom","timingControlPoint1y":0.10000000149011612,"timingControlPoint2x":1,"timingControlPoint1x":0.25,"timingControlPoint2y":1}],"keyTimes":[0,0.84999999999999998,0.94999999999999996,1],"additive":false,"values":[{"scalar":0.001},{"scalar":1.125},{"scalar":0.95199999999999996},{"scalar":0.99999999999999989}],"timeOffset":0,"autoreverses":false,"property":"transform.scale.xy","fillMode":"removed","duration":1,"beginTime":0},{"additive":false,"timeOffset":0,"beginTime":0.0001,"from":{"scalar":false},"repeatCount":0,"fillMode":"forwards","duration":0.99990000000000001,"autoreverses":false,"property":"hidden","to":{"scalar":false},"removedOnCompletion":true}],"removedOnCompletion":false}],"layers":[],"texturedRectangle":{"singleTextureOpacity":1,"textXHeight":0.70023696682464454,"textBaseline":0.94786802174355744,"isBackgroundTexture":true,"isVerticalText":false,"textColor":[0,0,0,1],"textureType":6},"initialState":{"affineTransform":[1,0,0,1,0,0],"masksToBounds":false,"rotation":0,"scale":1,"position":{"pointX":227.35400390625,"pointY":124.5},"width":345,"sublayerTransform":[1,0,0,0,0,1,0,0,0,0,1,0,0,0,0,1],"contentsRect":{"y":0,"x":0,"width":1,"height":1},"opacity":1,"edgeAntialiasingMask":0,"height":211,"hidden":true,"anchorPoint":{"pointX":0.5,"pointY":0.5}},"texture":"4A1483485811F20AF8B070A742C121A3"}]}]},"effects":[],"duration":1,"type":"buildIn","attributes":{"direction":0},"name":"apple:bc-pop","objectID":"5009FB8B-8410-482E-9042-03C87056AD2D"}],"duration":1,"type":"buildIn","attributes":{"direction":0},"name":"apple:bc-pop","objectID":"FB3377F4-D05D-46FE-B488-6DE00A805E0D"}],"automaticPlay":true,"hyperlinks":[],"accessibility":[{"text":"images-3.jpg","targetRectangle":{"y":-86,"x":1358,"width":222,"height":227}},{"text":" v","targetRectangle":{"y":-162,"x":51.073193359375011,"width":310.89999999999998,"height":562}},{"text":"￼","targetRectangle":{"y":687,"x":627.99999934434891,"width":24,"height":19}}],"baseLayer":{"animations":[],"initialState":{"affineTransform":[1,0,0,1,0,0],"masksToBounds":false,"rotation":0,"scale":1,"position":{"pointX":640,"pointY":360},"width":1280,"sublayerTransform":[1,0,0,0,0,1,0,0,0,0,1,0,0,0,0,1],"contentsRect":{"y":0,"x":0,"width":1,"height":1},"opacity":1,"edgeAntialiasingMask":251658240,"height":720,"hidden":false,"anchorPoint":{"pointX":0.5,"pointY":0.5}},"layers":[{"animations":[],"initialState":{"affineTransform":[1,0,0,1,0,0],"masksToBounds":false,"rotation":0,"scale":1,"position":{"pointX":640,"pointY":360},"width":1280,"sublayerTransform":[1,0,0,0,0,1,0,0,0,0,1,0,0,0,0,1],"contentsRect":{"y":0,"x":0,"width":1,"height":1},"opacity":1,"edgeAntialiasingMask":251658240,"height":720,"hidden":false,"anchorPoint":{"pointX":0.5,"pointY":0.5}},"layers":[{"animations":[],"initialState":{"affineTransform":[1,0,0,1,0,0],"masksToBounds":false,"rotation":0,"scale":1,"position":{"pointX":640,"pointY":360},"width":1280,"sublayerTransform":[1,0,0,0,0,1,0,0,0,0,1,0,0,0,0,1],"contentsRect":{"y":0,"x":0,"width":1,"height":1},"opacity":1,"edgeAntialiasingMask":251658240,"height":720,"hidden":false,"anchorPoint":{"pointX":0.5,"pointY":0.5}},"layers":[{"animations":[],"layers":[],"texturedRectangle":{"isBackgroundTexture":true,"singleTextureOpacity":1,"textureType":1,"textBaseline":0,"textXHeight":0,"isVerticalText":false},"initialState":{"affineTransform":[1,0,0,1,0,0],"masksToBounds":false,"rotation":0,"scale":1,"position":{"pointX":640,"pointY":360},"width":1280,"sublayerTransform":[1,0,0,0,0,1,0,0,0,0,1,0,0,0,0,1],"contentsRect":{"y":0,"x":0,"width":1,"height":1},"opacity":1,"edgeAntialiasingMask":0,"height":720,"hidden":false,"anchorPoint":{"pointX":0.5,"pointY":0.5}},"texture":"2F02F0C77F8F15244453071F240333F3"}]}]},{"animations":[],"initialState":{"affineTransform":[1,0,0,1,0,0],"masksToBounds":false,"rotation":0,"scale":1,"position":{"pointX":640,"pointY":360},"width":1280,"sublayerTransform":[1,0,0,0,0,1,0,0,0,0,1,0,0,0,0,1],"contentsRect":{"y":0,"x":0,"width":1,"height":1},"opacity":1,"edgeAntialiasingMask":251658240,"height":720,"hidden":false,"anchorPoint":{"pointX":0.5,"pointY":0.5}},"layers":[{"animations":[],"initialState":{"affineTransform":[1,0,0,1,0,0],"masksToBounds":false,"rotation":0,"scale":1,"position":{"pointX":797.0147705078125,"pointY":117},"width":553,"sublayerTransform":[1,0,0,0,0,1,0,0,0,0,1,0,0,0,0,1],"contentsRect":{"y":0,"x":0,"width":1,"height":1},"opacity":1,"edgeAntialiasingMask":251658240,"height":144,"hidden":false,"anchorPoint":{"pointX":0.5,"pointY":0.5}},"objectID":"FB3377F4-D05D-46FE-B488-6DE00A805E0D","layers":[{"animations":[],"layers":[],"texturedRectangle":{"singleTextureOpacity":1,"textXHeight":1.0260416666666667,"textBaseline":1.0625010596381292,"isBackgroundTexture":true,"isVerticalText":false,"textColor":[0,0,0,1],"textureType":6},"initialState":{"affineTransform":[1,0,0,1,0,0],"masksToBounds":false,"rotation":0,"scale":1,"position":{"pointX":304.9852294921875,"pointY":138},"width":553,"sublayerTransform":[1,0,0,0,0,1,0,0,0,0,1,0,0,0,0,1],"contentsRect":{"y":0,"x":0,"width":1,"height":1},"opacity":1,"edgeAntialiasingMask":0,"height":144,"hidden":true,"anchorPoint":{"pointX":0.5,"pointY":0.5}},"texture":"1347933E04244CB1F684C3CBCC629084"}]}]},{"animations":[],"initialState":{"affineTransform":[1,0,0,1,0,0],"masksToBounds":false,"rotation":0,"scale":1,"position":{"pointX":640,"pointY":360},"width":1280,"sublayerTransform":[1,0,0,0,0,1,0,0,0,0,1,0,0,0,0,1],"contentsRect":{"y":0,"x":0,"width":1,"height":1},"opacity":1,"edgeAntialiasingMask":251658240,"height":720,"hidden":false,"anchorPoint":{"pointX":0.5,"pointY":0.5}},"layers":[{"animations":[],"initialState":{"affineTransform":[1,0,0,1,0,0],"masksToBounds":false,"rotation":0,"scale":1,"position":{"pointX":350.5,"pointY":504.152587890625},"width":357,"sublayerTransform":[1,0,0,0,0,1,0,0,0,0,1,0,0,0,0,1],"contentsRect":{"y":0,"x":0,"width":1,"height":1},"opacity":1,"edgeAntialiasingMask":251658240,"height":357,"hidden":false,"anchorPoint":{"pointX":0.5,"pointY":0.5}},"objectID":"FBE84E8B-A122-4C17-816E-B2840CD504E5","layers":[{"animations":[],"layers":[],"texturedRectangle":{"isBackgroundTexture":true,"singleTextureOpacity":1,"textureType":5,"textBaseline":0,"textXHeight":0,"isVerticalText":false},"initialState":{"affineTransform":[1,0,0,1,0,0],"masksToBounds":false,"rotation":0,"scale":1,"position":{"pointX":177.5,"pointY":176.847412109375},"width":357,"sublayerTransform":[1,0,0,0,0,1,0,0,0,0,1,0,0,0,0,1],"contentsRect":{"y":0,"x":0,"width":1,"height":1},"opacity":1,"edgeAntialiasingMask":0,"height":357,"hidden":true,"anchorPoint":{"pointX":0.5,"pointY":0.5}},"texture":"F5118637D28E65DB0CFE82C14CCECE8E"}]}]},{"animations":[],"initialState":{"affineTransform":[1,0,0,1,0,0],"masksToBounds":false,"rotation":0,"scale":1,"position":{"pointX":640,"pointY":360},"width":1280,"sublayerTransform":[1,0,0,0,0,1,0,0,0,0,1,0,0,0,0,1],"contentsRect":{"y":0,"x":0,"width":1,"height":1},"opacity":1,"edgeAntialiasingMask":251658240,"height":720,"hidden":false,"anchorPoint":{"pointX":0.5,"pointY":0.5}},"layers":[{"animations":[],"initialState":{"affineTransform":[1,0,0,1,0,0],"masksToBounds":false,"rotation":0,"scale":1,"position":{"pointX":160.023193359375,"pointY":-61.5},"width":304,"sublayerTransform":[1,0,0,0,0,1,0,0,0,0,1,0,0,0,0,1],"contentsRect":{"y":0,"x":0,"width":1,"height":1},"opacity":1,"edgeAntialiasingMask":251658240,"height":209,"hidden":false,"anchorPoint":{"pointX":0.5,"pointY":0.5}},"layers":[{"animations":[],"initialState":{"affineTransform":[1,0,0,1,0,0],"masksToBounds":false,"rotation":0,"scale":1,"position":{"pointX":631.976806640625,"pointY":526},"width":304,"sublayerTransform":[1,0,0,0,0,1,0,0,0,0,1,-0.0005251186870016398,0,0,0,1],"contentsRect":{"y":0,"x":0,"width":1,"height":1},"opacity":1,"edgeAntialiasingMask":251658240,"height":209,"hidden":false,"anchorPoint":{"pointX":2.0788710744757402,"pointY":2.5167464114832536}},"layers":[{"animations":[],"layers":[],"texturedRectangle":{"singleTextureOpacity":1,"textXHeight":0.99869856459330153,"textBaseline":0.99751332844273322,"isBackgroundTexture":true,"isVerticalText":false,"textColor":[0,0,0,1],"textureType":6},"initialState":{"affineTransform":[1,0,0,1,0,0],"masksToBounds":false,"rotation":0,"scale":1,"position":{"pointX":194.976806640625,"pointY":396.5},"width":304,"sublayerTransform":[1,0,0,0,0,1,0,0,0,0,1,0,0,0,0,1],"contentsRect":{"y":0,"x":0,"width":1,"height":1},"opacity":1,"edgeAntialiasingMask":0,"height":209,"hidden":false,"anchorPoint":{"pointX":0.5,"pointY":0.5}},"texture":"C30918506A3DD362A001CD80A988B4D7"}]}]}]},{"animations":[],"initialState":{"affineTransform":[1,0,0,1,0,0],"masksToBounds":false,"rotation":0,"scale":1,"position":{"pointX":640,"pointY":360},"width":1280,"sublayerTransform":[1,0,0,0,0,1,0,0,0,0,1,0,0,0,0,1],"contentsRect":{"y":0,"x":0,"width":1,"height":1},"opacity":1,"edgeAntialiasingMask":251658240,"height":720,"hidden":false,"anchorPoint":{"pointX":0.5,"pointY":0.5}},"layers":[{"animations":[],"initialState":{"affineTransform":[1,0,0,1,0,0],"masksToBounds":false,"rotation":0,"scale":1,"position":{"pointX":636.99999934434891,"pointY":690},"width":27,"sublayerTransform":[1,0,0,0,0,1,0,0,0,0,1,0,0,0,0,1],"contentsRect":{"y":0,"x":0,"width":1,"height":1},"opacity":1,"edgeAntialiasingMask":251658240,"height":14,"hidden":false,"anchorPoint":{"pointX":0.5,"pointY":0.5}},"layers":[{"animations":[],"initialState":{"affineTransform":[1,0,0,1,0,0],"masksToBounds":false,"rotation":0,"scale":1,"position":{"pointX":16.500000655651093,"pointY":-323},"width":27,"sublayerTransform":[1,0,0,0,0,1,0,0,0,0,1,-0.0005251186870016398,0,0,0,1],"contentsRect":{"y":0,"x":0,"width":1,"height":1},"opacity":1,"edgeAntialiasingMask":251658240,"height":14,"hidden":false,"anchorPoint":{"pointX":0.61111113539448492,"pointY":-23.071428571428573}},"layers":[{"animations":[],"layers":[],"texturedRectangle":{"singleTextureOpacity":1,"textXHeight":0.5139508928571429,"textBaseline":0.8794642857142857,"isBackgroundTexture":true,"isVerticalText":false,"textColor":[0,0,0,1],"textureType":6},"initialState":{"affineTransform":[1,0,0,1,0,0],"masksToBounds":false,"rotation":0,"scale":1,"position":{"pointX":16.000000655651093,"pointY":14},"width":27,"sublayerTransform":[1,0,0,0,0,1,0,0,0,0,1,0,0,0,0,1],"contentsRect":{"y":0,"x":0,"width":1,"height":1},"opacity":1,"edgeAntialiasingMask":0,"height":14,"hidden":false,"anchorPoint":{"pointX":0.5,"pointY":0.5}},"texture":"5840FDD888AEFE7FEE4D3E821FDD3156"}]}]}]},{"animations":[],"initialState":{"affineTransform":[1,0,0,1,0,0],"masksToBounds":false,"rotation":0,"scale":1,"position":{"pointX":640,"pointY":360},"width":1280,"sublayerTransform":[1,0,0,0,0,1,0,0,0,0,1,0,0,0,0,1],"contentsRect":{"y":0,"x":0,"width":1,"height":1},"opacity":1,"edgeAntialiasingMask":251658240,"height":720,"hidden":false,"anchorPoint":{"pointX":0.5,"pointY":0.5}},"layers":[{"animations":[],"initialState":{"affineTransform":[1,0,0,1,0,0],"masksToBounds":false,"rotation":0,"scale":1,"position":{"pointX":812.64599609375,"pointY":479.5},"width":345,"sublayerTransform":[1,0,0,0,0,1,0,0,0,0,1,0,0,0,0,1],"contentsRect":{"y":0,"x":0,"width":1,"height":1},"opacity":1,"edgeAntialiasingMask":251658240,"height":211,"hidden":false,"anchorPoint":{"pointX":0.5,"pointY":0.5}},"objectID":"5009FB8B-8410-482E-9042-03C87056AD2D","layers":[{"animations":[],"layers":[],"texturedRectangle":{"singleTextureOpacity":1,"textXHeight":0.70023696682464454,"textBaseline":0.94786802174355744,"isBackgroundTexture":true,"isVerticalText":false,"textColor":[0,0,0,1],"textureType":6},"initialState":{"affineTransform":[1,0,0,1,0,0],"masksToBounds":false,"rotation":0,"scale":1,"position":{"pointX":227.35400390625,"pointY":124.5},"width":345,"sublayerTransform":[1,0,0,0,0,1,0,0,0,0,1,0,0,0,0,1],"contentsRect":{"y":0,"x":0,"width":1,"height":1},"opacity":1,"edgeAntialiasingMask":0,"height":211,"hidden":true,"anchorPoint":{"pointX":0.5,"pointY":0.5}},"texture":"4A1483485811F20AF8B070A742C121A3"}]}]},{"animations":[],"initialState":{"affineTransform":[1,0,0,1,0,0],"masksToBounds":false,"rotation":0,"scale":1,"position":{"pointX":640,"pointY":360},"width":1280,"sublayerTransform":[1,0,0,0,0,1,0,0,0,0,1,0,0,0,0,1],"contentsRect":{"y":0,"x":0,"width":1,"height":1},"opacity":1,"edgeAntialiasingMask":251658240,"height":720,"hidden":false,"anchorPoint":{"pointX":0.5,"pointY":0.5}},"layers":[{"animations":[],"initialState":{"affineTransform":[1,0,0,1,0,0],"masksToBounds":false,"rotation":0,"scale":1,"position":{"pointX":1470,"pointY":28.5},"width":224,"sublayerTransform":[1,0,0,0,0,1,0,0,0,0,1,0,0,0,0,1],"contentsRect":{"y":0,"x":0,"width":1,"height":1},"opacity":1,"edgeAntialiasingMask":251658240,"height":229,"hidden":false,"anchorPoint":{"pointX":0.5,"pointY":0.5}},"layers":[{"animations":[],"initialState":{"affineTransform":[1,0,0,1,0,0],"masksToBounds":false,"rotation":0,"scale":1,"position":{"pointX":-718,"pointY":446},"width":224,"sublayerTransform":[1,0,0,0,0,1,0,0,0,0,1,-0.0005251186870016398,0,0,0,1],"contentsRect":{"y":0,"x":0,"width":1,"height":1},"opacity":1,"edgeAntialiasingMask":251658240,"height":229,"hidden":false,"anchorPoint":{"pointX":-3.2053571428571428,"pointY":1.9475982532751093}},"layers":[{"animations":[],"layers":[],"texturedRectangle":{"isBackgroundTexture":true,"singleTextureOpacity":1,"textureType":5,"textBaseline":0,"textXHeight":0,"isVerticalText":false},"initialState":{"affineTransform":[1,0,0,1,0,0],"masksToBounds":false,"rotation":0,"scale":1,"position":{"pointX":111,"pointY":113.5},"width":224,"sublayerTransform":[1,0,0,0,0,1,0,0,0,0,1,0,0,0,0,1],"contentsRect":{"y":0,"x":0,"width":1,"height":1},"opacity":1,"edgeAntialiasingMask":0,"height":229,"hidden":false,"anchorPoint":{"pointX":0.5,"pointY":0.5}},"texture":"9B0CE0A95728ED838AEA01C26CB7FA57"}]}]}]}]}},{"effects":[{"beginTime":0.5,"baseLayer":{"animations":[],"initialState":{"affineTransform":[1,0,0,1,0,0],"masksToBounds":false,"rotation":0,"scale":1,"position":{"pointX":640,"pointY":360},"width":1280,"sublayerTransform":[1,0,0,0,0,1,0,0,0,0,1,0,0,0,0,1],"contentsRect":{"y":0,"x":0,"width":1,"height":1},"opacity":1,"edgeAntialiasingMask":251658240,"height":720,"hidden":false,"anchorPoint":{"pointX":0.5,"pointY":0.5}},"objectID":"0","layers":[{"animations":[],"initialState":{"affineTransform":[1,0,0,1,0,0],"masksToBounds":false,"rotation":0,"scale":1,"position":{"pointX":640,"pointY":360},"width":1280,"sublayerTransform":[1,0,0,0,0,1,0,0,0,0,1,-0.0005251186870016398,0,0,0,1],"contentsRect":{"y":0,"x":0,"width":1,"height":1},"opacity":1,"edgeAntialiasingMask":251658240,"height":720,"hidden":false,"anchorPoint":{"pointX":0.5,"pointY":0.5}},"layers":[{"animations":[],"initialState":{"affineTransform":[1,0,0,1,0,0],"masksToBounds":false,"rotation":0,"scale":1,"position":{"pointX":640,"pointY":360},"width":1280,"sublayerTransform":[1,0,0,0,0,1,0,0,0,0,1,0,0,0,0,1],"contentsRect":{"y":0,"x":0,"width":1,"height":1},"opacity":1,"edgeAntialiasingMask":251658240,"height":720,"hidden":false,"anchorPoint":{"pointX":0.5,"pointY":0.5}},"layers":[{"animations":[{"repeatCount":0,"removedOnCompletion":false,"from":{"scalar":false},"timingFunction":"EaseInEaseOut","additive":false,"timeOffset":0,"autoreverses":false,"property":"hidden","fillMode":"both","duration":1,"beginTime":0,"to":{"scalar":false}}],"layers":[],"texturedRectangle":{"isBackgroundTexture":true,"singleTextureOpacity":1,"textureType":1,"textBaseline":0,"textXHeight":0,"isVerticalText":false},"initialState":{"affineTransform":[1,0,0,1,0,0],"masksToBounds":false,"rotation":0,"scale":1,"position":{"pointX":640,"pointY":360},"width":1280,"sublayerTransform":[1,0,0,0,0,1,0,0,0,0,1,0,0,0,0,1],"contentsRect":{"y":0,"x":0,"width":1,"height":1},"opacity":1,"edgeAntialiasingMask":0,"height":720,"hidden":false,"anchorPoint":{"pointX":0.5,"pointY":0.5}},"texture":"2F02F0C77F8F15244453071F240333F3"}]},{"animations":[],"initialState":{"affineTransform":[1,0,0,1,0,0],"masksToBounds":false,"rotation":0,"scale":1,"position":{"pointX":640,"pointY":360},"width":1280,"sublayerTransform":[1,0,0,0,0,1,0,0,0,0,1,0,0,0,0,1],"contentsRect":{"y":0,"x":0,"width":1,"height":1},"opacity":1,"edgeAntialiasingMask":251658240,"height":720,"hidden":false,"anchorPoint":{"pointX":0.5,"pointY":0.5}},"layers":[{"animations":[{"repeatCount":0,"removedOnCompletion":false,"from":{"scalar":1},"timingFunction":"EaseInEaseOut","additive":false,"timeOffset":0,"autoreverses":false,"property":"opacity","fillMode":"both","duration":1,"beginTime":0,"to":{"scalar":0}}],"layers":[],"texturedRectangle":{"isBackgroundTexture":true,"singleTextureOpacity":1,"textureType":1,"textBaseline":0,"textXHeight":0,"isVerticalText":false},"initialState":{"affineTransform":[1,0,0,1,0,0],"masksToBounds":false,"rotation":0,"scale":1,"position":{"pointX":640,"pointY":360},"width":1280,"sublayerTransform":[1,0,0,0,0,1,0,0,0,0,1,0,0,0,0,1],"contentsRect":{"y":0,"x":0,"width":1,"height":1},"opacity":1,"edgeAntialiasingMask":0,"height":720,"hidden":false,"anchorPoint":{"pointX":0.5,"pointY":0.5}},"texture":"2F02F0C77F8F15244453071F240333F3"}]}]},{"animations":[],"initialState":{"affineTransform":[1,0,0,1,0,0],"masksToBounds":false,"rotation":0,"scale":1,"position":{"pointX":797.0147705078125,"pointY":117},"width":553,"sublayerTransform":[1,0,0,0,0,1,0,0,0,0,1,0,0,0,0,1],"contentsRect":{"y":0,"x":0,"width":1,"height":1},"opacity":1,"edgeAntialiasingMask":251658240,"height":144,"hidden":false,"anchorPoint":{"pointX":0.5,"pointY":0.5}},"layers":[{"animations":[],"initialState":{"affineTransform":[1,0,0,1,0,0],"masksToBounds":false,"rotation":0,"scale":1,"position":{"pointX":119.4852294921875,"pointY":315},"width":553,"sublayerTransform":[1,0,0,0,0,1,0,0,0,0,1,-0.0005251186870016398,0,0,0,1],"contentsRect":{"y":0,"x":0,"width":1,"height":1},"opacity":1,"edgeAntialiasingMask":251658240,"height":144,"hidden":false,"anchorPoint":{"pointX":0.21606732277068263,"pointY":2.1875}},"layers":[{"animations":[{"additive":false,"timeOffset":0,"beginTime":0,"repeatCount":0,"fillMode":"both","duration":1,"autoreverses":false,"animations":[{"repeatCount":0,"removedOnCompletion":true,"from":{"scalar":1},"timingFunction":"EaseOut","additive":false,"timeOffset":0,"autoreverses":false,"property":"opacity","fillMode":"both","duration":0.27999999999999997,"beginTime":0,"to":{"scalar":0}},{"repeatCount":0,"removedOnCompletion":true,"from":{"scalar":0},"timingFunction":"EaseOut","additive":false,"timeOffset":0,"autoreverses":false,"property":"zPosition","fillMode":"both","duration":0.27999999999999997,"beginTime":0,"to":{"scalar":896}},{"additive":false,"timeOffset":0,"beginTime":0,"from":{"scalar":false},"repeatCount":0,"fillMode":"both","duration":1,"autoreverses":false,"property":"hidden","to":{"scalar":false},"removedOnCompletion":true}],"removedOnCompletion":false}],"layers":[],"texturedRectangle":{"singleTextureOpacity":1,"textXHeight":1.0260416666666667,"textBaseline":1.0625010596381292,"isBackgroundTexture":true,"isVerticalText":false,"textColor":[0,0,0,1],"textureType":6},"initialState":{"affineTransform":[1,0,0,1,0,0],"masksToBounds":false,"rotation":0,"scale":1,"position":{"pointX":304.9852294921875,"pointY":138},"width":553,"sublayerTransform":[1,0,0,0,0,1,0,0,0,0,1,0,0,0,0,1],"contentsRect":{"y":0,"x":0,"width":1,"height":1},"opacity":1,"edgeAntialiasingMask":0,"height":144,"hidden":false,"anchorPoint":{"pointX":0.5,"pointY":0.5}},"texture":"1347933E04244CB1F684C3CBCC629084"}]}]},{"animations":[],"initialState":{"affineTransform":[1,0,0,1,0,0],"masksToBounds":false,"rotation":0,"scale":1,"position":{"pointX":350.5,"pointY":504.152587890625},"width":357,"sublayerTransform":[1,0,0,0,0,1,0,0,0,0,1,0,0,0,0,1],"contentsRect":{"y":0,"x":0,"width":1,"height":1},"opacity":1,"edgeAntialiasingMask":251658240,"height":357,"hidden":false,"anchorPoint":{"pointX":0.5,"pointY":0.5}},"layers":[{"animations":[],"initialState":{"affineTransform":[1,0,0,1,0,0],"masksToBounds":false,"rotation":0,"scale":1,"position":{"pointX":468,"pointY":34.347412109375},"width":357,"sublayerTransform":[1,0,0,0,0,1,0,0,0,0,1,-0.0005251186870016398,0,0,0,1],"contentsRect":{"y":0,"x":0,"width":1,"height":1},"opacity":1,"edgeAntialiasingMask":251658240,"height":357,"hidden":false,"anchorPoint":{"pointX":1.3109243697478992,"pointY":0.096211238401610638}},"layers":[{"animations":[{"additive":false,"timeOffset":0,"beginTime":0,"repeatCount":0,"fillMode":"both","duration":1,"autoreverses":false,"animations":[{"repeatCount":0,"removedOnCompletion":true,"from":{"scalar":1},"timingFunction":"EaseOut","additive":false,"timeOffset":0,"autoreverses":false,"property":"opacity","fillMode":"both","duration":0.27999999999999997,"beginTime":0.069999999999999993,"to":{"scalar":0}},{"repeatCount":0,"removedOnCompletion":true,"from":{"scalar":0},"timingFunction":"EaseOut","additive":false,"timeOffset":0,"autoreverses":false,"property":"zPosition","fillMode":"both","duration":0.27999999999999997,"beginTime":0.069999999999999993,"to":{"scalar":896}},{"additive":false,"timeOffset":0,"beginTime":0,"from":{"scalar":false},"repeatCount":0,"fillMode":"both","duration":1,"autoreverses":false,"property":"hidden","to":{"scalar":false},"removedOnCompletion":true}],"removedOnCompletion":false}],"layers":[],"texturedRectangle":{"isBackgroundTexture":true,"singleTextureOpacity":1,"textureType":5,"textBaseline":0,"textXHeight":0,"isVerticalText":false},"initialState":{"affineTransform":[1,0,0,1,0,0],"masksToBounds":false,"rotation":0,"scale":1,"position":{"pointX":177.5,"pointY":176.847412109375},"width":357,"sublayerTransform":[1,0,0,0,0,1,0,0,0,0,1,0,0,0,0,1],"contentsRect":{"y":0,"x":0,"width":1,"height":1},"opacity":1,"edgeAntialiasingMask":0,"height":357,"hidden":false,"anchorPoint":{"pointX":0.5,"pointY":0.5}},"texture":"F5118637D28E65DB0CFE82C14CCECE8E"}]}]},{"animations":[],"initialState":{"affineTransform":[1,0,0,1,0,0],"masksToBounds":false,"rotation":0,"scale":1,"position":{"pointX":160.023193359375,"pointY":-61.5},"width":304,"sublayerTransform":[1,0,0,0,0,1,0,0,0,0,1,0,0,0,0,1],"contentsRect":{"y":0,"x":0,"width":1,"height":1},"opacity":1,"edgeAntialiasingMask":251658240,"height":209,"hidden":false,"anchorPoint":{"pointX":0.5,"pointY":0.5}},"layers":[{"animations":[],"initialState":{"affineTransform":[1,0,0,1,0,0],"masksToBounds":false,"rotation":0,"scale":1,"position":{"pointX":631.976806640625,"pointY":526},"width":304,"sublayerTransform":[1,0,0,0,0,1,0,0,0,0,1,-0.0005251186870016398,0,0,0,1],"contentsRect":{"y":0,"x":0,"width":1,"height":1},"opacity":1,"edgeAntialiasingMask":251658240,"height":209,"hidden":false,"anchorPoint":{"pointX":2.0788710744757402,"pointY":2.5167464114832536}},"layers":[{"animations":[{"additive":false,"timeOffset":0,"beginTime":0,"repeatCount":0,"fillMode":"both","duration":1,"autoreverses":false,"animations":[{"repeatCount":0,"removedOnCompletion":true,"from":{"scalar":1},"timingFunction":"EaseOut","additive":false,"timeOffset":0,"autoreverses":false,"property":"opacity","fillMode":"both","duration":0.27999999999999997,"beginTime":0.13999999999999999,"to":{"scalar":0}},{"repeatCount":0,"removedOnCompletion":true,"from":{"scalar":0},"timingFunction":"EaseOut","additive":false,"timeOffset":0,"autoreverses":false,"property":"zPosition","fillMode":"both","duration":0.27999999999999997,"beginTime":0.13999999999999999,"to":{"scalar":896}},{"additive":false,"timeOffset":0,"beginTime":0,"from":{"scalar":false},"repeatCount":0,"fillMode":"both","duration":1,"autoreverses":false,"property":"hidden","to":{"scalar":false},"removedOnCompletion":true}],"removedOnCompletion":false}],"layers":[],"texturedRectangle":{"singleTextureOpacity":1,"textXHeight":0.99869856459330153,"textBaseline":0.99751332844273322,"isBackgroundTexture":true,"isVerticalText":false,"textColor":[0,0,0,1],"textureType":6},"initialState":{"affineTransform":[1,0,0,1,0,0],"masksToBounds":false,"rotation":0,"scale":1,"position":{"pointX":194.976806640625,"pointY":396.5},"width":304,"sublayerTransform":[1,0,0,0,0,1,0,0,0,0,1,0,0,0,0,1],"contentsRect":{"y":0,"x":0,"width":1,"height":1},"opacity":1,"edgeAntialiasingMask":0,"height":209,"hidden":false,"anchorPoint":{"pointX":0.5,"pointY":0.5}},"texture":"C30918506A3DD362A001CD80A988B4D7"}]}]},{"animations":[],"initialState":{"affineTransform":[1,0,0,1,0,0],"masksToBounds":false,"rotation":0,"scale":1,"position":{"pointX":636.99999934434891,"pointY":690},"width":27,"sublayerTransform":[1,0,0,0,0,1,0,0,0,0,1,0,0,0,0,1],"contentsRect":{"y":0,"x":0,"width":1,"height":1},"opacity":1,"edgeAntialiasingMask":251658240,"height":14,"hidden":false,"anchorPoint":{"pointX":0.5,"pointY":0.5}},"layers":[{"animations":[],"initialState":{"affineTransform":[1,0,0,1,0,0],"masksToBounds":false,"rotation":0,"scale":1,"position":{"pointX":16.500000655651093,"pointY":-323},"width":27,"sublayerTransform":[1,0,0,0,0,1,0,0,0,0,1,-0.0005251186870016398,0,0,0,1],"contentsRect":{"y":0,"x":0,"width":1,"height":1},"opacity":1,"edgeAntialiasingMask":251658240,"height":14,"hidden":false,"anchorPoint":{"pointX":0.61111113539448492,"pointY":-23.071428571428573}},"layers":[{"animations":[{"additive":false,"timeOffset":0,"beginTime":0,"repeatCount":0,"fillMode":"both","duration":1,"autoreverses":false,"animations":[{"repeatCount":0,"removedOnCompletion":true,"from":{"scalar":1},"timingFunction":"EaseOut","additive":false,"timeOffset":0,"autoreverses":false,"property":"opacity","fillMode":"both","duration":0.27999999999999997,"beginTime":0.20999999999999999,"to":{"scalar":0}},{"repeatCount":0,"removedOnCompletion":true,"from":{"scalar":0},"timingFunction":"EaseOut","additive":false,"timeOffset":0,"autoreverses":false,"property":"zPosition","fillMode":"both","duration":0.27999999999999997,"beginTime":0.20999999999999999,"to":{"scalar":896}},{"additive":false,"timeOffset":0,"beginTime":0,"from":{"scalar":false},"repeatCount":0,"fillMode":"both","duration":1,"autoreverses":false,"property":"hidden","to":{"scalar":false},"removedOnCompletion":true}],"removedOnCompletion":false}],"layers":[],"texturedRectangle":{"singleTextureOpacity":1,"textXHeight":0.5139508928571429,"textBaseline":0.8794642857142857,"isBackgroundTexture":true,"isVerticalText":false,"textColor":[0,0,0,1],"textureType":6},"initialState":{"affineTransform":[1,0,0,1,0,0],"masksToBounds":false,"rotation":0,"scale":1,"position":{"pointX":16.000000655651093,"pointY":14},"width":27,"sublayerTransform":[1,0,0,0,0,1,0,0,0,0,1,0,0,0,0,1],"contentsRect":{"y":0,"x":0,"width":1,"height":1},"opacity":1,"edgeAntialiasingMask":0,"height":14,"hidden":false,"anchorPoint":{"pointX":0.5,"pointY":0.5}},"texture":"5840FDD888AEFE7FEE4D3E821FDD3156"}]}]},{"animations":[],"initialState":{"affineTransform":[1,0,0,1,0,0],"masksToBounds":false,"rotation":0,"scale":1,"position":{"pointX":812.64599609375,"pointY":479.5},"width":345,"sublayerTransform":[1,0,0,0,0,1,0,0,0,0,1,0,0,0,0,1],"contentsRect":{"y":0,"x":0,"width":1,"height":1},"opacity":1,"edgeAntialiasingMask":251658240,"height":211,"hidden":false,"anchorPoint":{"pointX":0.5,"pointY":0.5}},"layers":[{"animations":[],"initialState":{"affineTransform":[1,0,0,1,0,0],"masksToBounds":false,"rotation":0,"scale":1,"position":{"pointX":-0.14599609375,"pointY":-14},"width":345,"sublayerTransform":[1,0,0,0,0,1,0,0,0,0,1,-0.0005251186870016398,0,0,0,1],"contentsRect":{"y":0,"x":0,"width":1,"height":1},"opacity":1,"edgeAntialiasingMask":251658240,"height":211,"hidden":false,"anchorPoint":{"pointX":-0.00042317708333333335,"pointY":-0.066350710900473939}},"layers":[{"animations":[{"additive":false,"timeOffset":0,"beginTime":0,"repeatCount":0,"fillMode":"both","duration":1,"autoreverses":false,"animations":[{"repeatCount":0,"removedOnCompletion":true,"from":{"scalar":1},"timingFunction":"EaseOut","additive":false,"timeOffset":0,"autoreverses":false,"property":"opacity","fillMode":"both","duration":0.27999999999999997,"beginTime":0.27999999999999997,"to":{"scalar":0}},{"repeatCount":0,"removedOnCompletion":true,"from":{"scalar":0},"timingFunction":"EaseOut","additive":false,"timeOffset":0,"autoreverses":false,"property":"zPosition","fillMode":"both","duration":0.27999999999999997,"beginTime":0.27999999999999997,"to":{"scalar":896}},{"additive":false,"timeOffset":0,"beginTime":0,"from":{"scalar":false},"repeatCount":0,"fillMode":"both","duration":1,"autoreverses":false,"property":"hidden","to":{"scalar":false},"removedOnCompletion":true}],"removedOnCompletion":false}],"layers":[],"texturedRectangle":{"singleTextureOpacity":1,"textXHeight":0.70023696682464454,"textBaseline":0.94786802174355744,"isBackgroundTexture":true,"isVerticalText":false,"textColor":[0,0,0,1],"textureType":6},"initialState":{"affineTransform":[1,0,0,1,0,0],"masksToBounds":false,"rotation":0,"scale":1,"position":{"pointX":227.35400390625,"pointY":124.5},"width":345,"sublayerTransform":[1,0,0,0,0,1,0,0,0,0,1,0,0,0,0,1],"contentsRect":{"y":0,"x":0,"width":1,"height":1},"opacity":1,"edgeAntialiasingMask":0,"height":211,"hidden":false,"anchorPoint":{"pointX":0.5,"pointY":0.5}},"texture":"4A1483485811F20AF8B070A742C121A3"}]}]},{"animations":[],"initialState":{"affineTransform":[1,0,0,1,0,0],"masksToBounds":false,"rotation":0,"scale":1,"position":{"pointX":1470,"pointY":28.5},"width":224,"sublayerTransform":[1,0,0,0,0,1,0,0,0,0,1,0,0,0,0,1],"contentsRect":{"y":0,"x":0,"width":1,"height":1},"opacity":1,"edgeAntialiasingMask":251658240,"height":229,"hidden":false,"anchorPoint":{"pointX":0.5,"pointY":0.5}},"layers":[{"animations":[],"initialState":{"affineTransform":[1,0,0,1,0,0],"masksToBounds":false,"rotation":0,"scale":1,"position":{"pointX":-718,"pointY":446},"width":224,"sublayerTransform":[1,0,0,0,0,1,0,0,0,0,1,-0.0005251186870016398,0,0,0,1],"contentsRect":{"y":0,"x":0,"width":1,"height":1},"opacity":1,"edgeAntialiasingMask":251658240,"height":229,"hidden":false,"anchorPoint":{"pointX":-3.2053571428571428,"pointY":1.9475982532751093}},"layers":[{"animations":[{"additive":false,"timeOffset":0,"beginTime":0,"repeatCount":0,"fillMode":"both","duration":1,"autoreverses":false,"animations":[{"repeatCount":0,"removedOnCompletion":true,"from":{"scalar":1},"timingFunction":"EaseOut","additive":false,"timeOffset":0,"autoreverses":false,"property":"opacity","fillMode":"both","duration":0.27999999999999997,"beginTime":0.34999999999999992,"to":{"scalar":0}},{"repeatCount":0,"removedOnCompletion":true,"from":{"scalar":0},"timingFunction":"EaseOut","additive":false,"timeOffset":0,"autoreverses":false,"property":"zPosition","fillMode":"both","duration":0.27999999999999997,"beginTime":0.34999999999999992,"to":{"scalar":896}},{"additive":false,"timeOffset":0,"beginTime":0,"from":{"scalar":false},"repeatCount":0,"fillMode":"both","duration":1,"autoreverses":false,"property":"hidden","to":{"scalar":false},"removedOnCompletion":true}],"removedOnCompletion":false}],"layers":[],"texturedRectangle":{"isBackgroundTexture":true,"singleTextureOpacity":1,"textureType":5,"textBaseline":0,"textXHeight":0,"isVerticalText":false},"initialState":{"affineTransform":[1,0,0,1,0,0],"masksToBounds":false,"rotation":0,"scale":1,"position":{"pointX":111,"pointY":113.5},"width":224,"sublayerTransform":[1,0,0,0,0,1,0,0,0,0,1,0,0,0,0,1],"contentsRect":{"y":0,"x":0,"width":1,"height":1},"opacity":1,"edgeAntialiasingMask":0,"height":229,"hidden":false,"anchorPoint":{"pointX":0.5,"pointY":0.5}},"texture":"9B0CE0A95728ED838AEA01C26CB7FA57"}]}]},{"animations":[],"initialState":{"affineTransform":[1,0,0,1,0,0],"masksToBounds":false,"rotation":0,"scale":1,"position":{"pointX":123.023193359375,"pointY":69.5},"width":380,"sublayerTransform":[1,0,0,0,0,1,0,0,0,0,1,0,0,0,0,1],"contentsRect":{"y":0,"x":0,"width":1,"height":1},"opacity":1,"edgeAntialiasingMask":251658240,"height":209,"hidden":false,"anchorPoint":{"pointX":0.5,"pointY":0.5}},"layers":[{"animations":[],"initialState":{"affineTransform":[1,0,0,1,0,0],"masksToBounds":false,"rotation":0,"scale":1,"position":{"pointX":706.976806640625,"pointY":395},"width":380,"sublayerTransform":[1,0,0,0,0,1,0,0,0,0,1,-0.0005251186870016398,0,0,0,1],"contentsRect":{"y":0,"x":0,"width":1,"height":1},"opacity":1,"edgeAntialiasingMask":251658240,"height":209,"hidden":false,"anchorPoint":{"pointX":1.8604652806332236,"pointY":1.8899521531100478}},"layers":[{"animations":[{"additive":false,"timeOffset":0,"beginTime":0,"repeatCount":0,"fillMode":"both","duration":1,"autoreverses":false,"animations":[{"repeatCount":0,"removedOnCompletion":true,"from":{"scalar":0},"timingFunction":"EaseOut","additive":false,"timeOffset":0,"autoreverses":false,"property":"opacity","fillMode":"both","duration":0.27999999999999997,"beginTime":0.30000000000000004,"to":{"scalar":1}},{"repeatCount":0,"removedOnCompletion":true,"from":{"scalar":-4480},"timingFunction":"EaseOut","additive":false,"timeOffset":0,"autoreverses":false,"property":"zPosition","fillMode":"both","duration":0.27999999999999997,"beginTime":0.30000000000000004,"to":{"scalar":0}},{"additive":false,"timeOffset":0,"beginTime":0,"from":{"scalar":false},"repeatCount":0,"fillMode":"both","duration":1,"autoreverses":false,"property":"hidden","to":{"scalar":false},"removedOnCompletion":true}],"removedOnCompletion":false}],"layers":[],"texturedRectangle":{"singleTextureOpacity":1,"textXHeight":0.74688995215311005,"textBaseline":0.99521633312462621,"isBackgroundTexture":true,"isVerticalText":false,"textColor":[0,0,0,1],"textureType":6},"initialState":{"affineTransform":[1,0,0,1,0,0],"masksToBounds":false,"rotation":0,"scale":1,"position":{"pointX":206.976806640625,"pointY":271.5},"width":380,"sublayerTransform":[1,0,0,0,0,1,0,0,0,0,1,0,0,0,0,1],"contentsRect":{"y":0,"x":0,"width":1,"height":1},"opacity":1,"edgeAntialiasingMask":0,"height":209,"hidden":true,"anchorPoint":{"pointX":0.5,"pointY":0.5}},"texture":"A8288665C890835D50CBD17E8C8FEB9D"}]}]},{"animations":[],"initialState":{"affineTransform":[1,0,0,1,0,0],"masksToBounds":false,"rotation":0,"scale":1,"position":{"pointX":636.99999934434891,"pointY":690},"width":27,"sublayerTransform":[1,0,0,0,0,1,0,0,0,0,1,0,0,0,0,1],"contentsRect":{"y":0,"x":0,"width":1,"height":1},"opacity":1,"edgeAntialiasingMask":251658240,"height":14,"hidden":false,"anchorPoint":{"pointX":0.5,"pointY":0.5}},"layers":[{"animations":[],"initialState":{"affineTransform":[1,0,0,1,0,0],"masksToBounds":false,"rotation":0,"scale":1,"position":{"pointX":16.500000655651093,"pointY":-323},"width":27,"sublayerTransform":[1,0,0,0,0,1,0,0,0,0,1,-0.0005251186870016398,0,0,0,1],"contentsRect":{"y":0,"x":0,"width":1,"height":1},"opacity":1,"edgeAntialiasingMask":251658240,"height":14,"hidden":false,"anchorPoint":{"pointX":0.61111113539448492,"pointY":-23.071428571428573}},"layers":[{"animations":[{"additive":false,"timeOffset":0,"beginTime":0,"repeatCount":0,"fillMode":"both","duration":1,"autoreverses":false,"animations":[{"repeatCount":0,"removedOnCompletion":true,"from":{"scalar":0},"timingFunction":"EaseOut","additive":false,"timeOffset":0,"autoreverses":false,"property":"opacity","fillMode":"both","duration":0.27999999999999997,"beginTime":0.44,"to":{"scalar":1}},{"repeatCount":0,"removedOnCompletion":true,"from":{"scalar":-13440},"timingFunction":"EaseOut","additive":false,"timeOffset":0,"autoreverses":false,"property":"zPosition","fillMode":"both","duration":0.27999999999999997,"beginTime":0.44,"to":{"scalar":0}},{"additive":false,"timeOffset":0,"beginTime":0,"from":{"scalar":false},"repeatCount":0,"fillMode":"both","duration":1,"autoreverses":false,"property":"hidden","to":{"scalar":false},"removedOnCompletion":true}],"removedOnCompletion":false}],"layers":[],"texturedRectangle":{"singleTextureOpacity":1,"textXHeight":0.5139508928571429,"textBaseline":0.8794642857142857,"isBackgroundTexture":true,"isVerticalText":false,"textColor":[0,0,0,1],"textureType":6},"initialState":{"affineTransform":[1,0,0,1,0,0],"masksToBounds":false,"rotation":0,"scale":1,"position":{"pointX":16.000000655651093,"pointY":14},"width":27,"sublayerTransform":[1,0,0,0,0,1,0,0,0,0,1,0,0,0,0,1],"contentsRect":{"y":0,"x":0,"width":1,"height":1},"opacity":1,"edgeAntialiasingMask":0,"height":14,"hidden":true,"anchorPoint":{"pointX":0.5,"pointY":0.5}},"texture":"2CACF84A11B392050CFF2F099D092F82"}]}]},{"animations":[],"initialState":{"affineTransform":[1,0,0,1,0,0],"masksToBounds":false,"rotation":0,"scale":1,"position":{"pointX":1470,"pointY":28.5},"width":224,"sublayerTransform":[1,0,0,0,0,1,0,0,0,0,1,0,0,0,0,1],"contentsRect":{"y":0,"x":0,"width":1,"height":1},"opacity":1,"edgeAntialiasingMask":251658240,"height":229,"hidden":false,"anchorPoint":{"pointX":0.5,"pointY":0.5}},"layers":[{"animations":[],"initialState":{"affineTransform":[1,0,0,1,0,0],"masksToBounds":false,"rotation":0,"scale":1,"position":{"pointX":-718,"pointY":446},"width":224,"sublayerTransform":[1,0,0,0,0,1,0,0,0,0,1,-0.0005251186870016398,0,0,0,1],"contentsRect":{"y":0,"x":0,"width":1,"height":1},"opacity":1,"edgeAntialiasingMask":251658240,"height":229,"hidden":false,"anchorPoint":{"pointX":-3.2053571428571428,"pointY":1.9475982532751093}},"layers":[{"animations":[{"additive":false,"timeOffset":0,"beginTime":0,"repeatCount":0,"fillMode":"both","duration":1,"autoreverses":false,"animations":[{"repeatCount":0,"removedOnCompletion":true,"from":{"scalar":0},"timingFunction":"EaseOut","additive":false,"timeOffset":0,"autoreverses":false,"property":"opacity","fillMode":"both","duration":0.27999999999999997,"beginTime":0.57999999999999996,"to":{"scalar":1}},{"repeatCount":0,"removedOnCompletion":true,"from":{"scalar":-6720},"timingFunction":"EaseOut","additive":false,"timeOffset":0,"autoreverses":false,"property":"zPosition","fillMode":"both","duration":0.27999999999999997,"beginTime":0.57999999999999996,"to":{"scalar":0}},{"additive":false,"timeOffset":0,"beginTime":0,"from":{"scalar":false},"repeatCount":0,"fillMode":"both","duration":1,"autoreverses":false,"property":"hidden","to":{"scalar":false},"removedOnCompletion":true}],"removedOnCompletion":false}],"layers":[],"texturedRectangle":{"isBackgroundTexture":true,"singleTextureOpacity":1,"textureType":5,"textBaseline":0,"textXHeight":0,"isVerticalText":false},"initialState":{"affineTransform":[1,0,0,1,0,0],"masksToBounds":false,"rotation":0,"scale":1,"position":{"pointX":111,"pointY":113.5},"width":224,"sublayerTransform":[1,0,0,0,0,1,0,0,0,0,1,0,0,0,0,1],"contentsRect":{"y":0,"x":0,"width":1,"height":1},"opacity":1,"edgeAntialiasingMask":0,"height":229,"hidden":true,"anchorPoint":{"pointX":0.5,"pointY":0.5}},"texture":"453908F53C17B73A863A51D614A958E3"}]}]}]},"effects":[],"duration":1,"type":"transition","attributes":{"direction":0},"name":"apple:ca-zoom","objectID":"0"}],"automaticPlay":true,"hyperlinks":[],"accessibility":[{"text":"images-3.jpg","targetRectangle":{"y":-86,"x":1358,"width":222,"height":227}},{"text":" v","targetRectangle":{"y":-162,"x":51.073193359375011,"width":310.89999999999998,"height":562}},{"text":"vase","targetRectangle":{"y":49,"x":544.1397705078125,"width":568.75,"height":250}},{"text":"\/v\/","targetRectangle":{"y":378,"x":687.64599609375,"width":357,"height":250}},{"text":"Unknown.jpg","targetRectangle":{"y":325.652587890625,"x":172,"width":354.00003051757812,"height":354}},{"text":"￼","targetRectangle":{"y":687,"x":627.99999934434891,"width":24,"height":19}}],"baseLayer":{"animations":[],"initialState":{"affineTransform":[1,0,0,1,0,0],"masksToBounds":false,"rotation":0,"scale":1,"position":{"pointX":640,"pointY":360},"width":1280,"sublayerTransform":[1,0,0,0,0,1,0,0,0,0,1,0,0,0,0,1],"contentsRect":{"y":0,"x":0,"width":1,"height":1},"opacity":1,"edgeAntialiasingMask":251658240,"height":720,"hidden":false,"anchorPoint":{"pointX":0.5,"pointY":0.5}},"objectID":"0","layers":[{"animations":[],"initialState":{"affineTransform":[1,0,0,1,0,0],"masksToBounds":false,"rotation":0,"scale":1,"position":{"pointX":640,"pointY":360},"width":1280,"sublayerTransform":[1,0,0,0,0,1,0,0,0,0,1,-0.0005251186870016398,0,0,0,1],"contentsRect":{"y":0,"x":0,"width":1,"height":1},"opacity":1,"edgeAntialiasingMask":251658240,"height":720,"hidden":false,"anchorPoint":{"pointX":0.5,"pointY":0.5}},"layers":[{"animations":[],"initialState":{"affineTransform":[1,0,0,1,0,0],"masksToBounds":false,"rotation":0,"scale":1,"position":{"pointX":640,"pointY":360},"width":1280,"sublayerTransform":[1,0,0,0,0,1,0,0,0,0,1,0,0,0,0,1],"contentsRect":{"y":0,"x":0,"width":1,"height":1},"opacity":1,"edgeAntialiasingMask":251658240,"height":720,"hidden":false,"anchorPoint":{"pointX":0.5,"pointY":0.5}},"layers":[{"animations":[],"layers":[],"texturedRectangle":{"isBackgroundTexture":true,"singleTextureOpacity":1,"textureType":1,"textBaseline":0,"textXHeight":0,"isVerticalText":false},"initialState":{"affineTransform":[1,0,0,1,0,0],"masksToBounds":false,"rotation":0,"scale":1,"position":{"pointX":640,"pointY":360},"width":1280,"sublayerTransform":[1,0,0,0,0,1,0,0,0,0,1,0,0,0,0,1],"contentsRect":{"y":0,"x":0,"width":1,"height":1},"opacity":1,"edgeAntialiasingMask":0,"height":720,"hidden":false,"anchorPoint":{"pointX":0.5,"pointY":0.5}},"texture":"2F02F0C77F8F15244453071F240333F3"}]},{"animations":[],"initialState":{"affineTransform":[1,0,0,1,0,0],"masksToBounds":false,"rotation":0,"scale":1,"position":{"pointX":640,"pointY":360},"width":1280,"sublayerTransform":[1,0,0,0,0,1,0,0,0,0,1,0,0,0,0,1],"contentsRect":{"y":0,"x":0,"width":1,"height":1},"opacity":1,"edgeAntialiasingMask":251658240,"height":720,"hidden":false,"anchorPoint":{"pointX":0.5,"pointY":0.5}},"layers":[{"animations":[],"layers":[],"texturedRectangle":{"isBackgroundTexture":true,"singleTextureOpacity":1,"textureType":1,"textBaseline":0,"textXHeight":0,"isVerticalText":false},"initialState":{"affineTransform":[1,0,0,1,0,0],"masksToBounds":false,"rotation":0,"scale":1,"position":{"pointX":640,"pointY":360},"width":1280,"sublayerTransform":[1,0,0,0,0,1,0,0,0,0,1,0,0,0,0,1],"contentsRect":{"y":0,"x":0,"width":1,"height":1},"opacity":1,"edgeAntialiasingMask":0,"height":720,"hidden":false,"anchorPoint":{"pointX":0.5,"pointY":0.5}},"texture":"2F02F0C77F8F15244453071F240333F3"}]}]},{"animations":[],"initialState":{"affineTransform":[1,0,0,1,0,0],"masksToBounds":false,"rotation":0,"scale":1,"position":{"pointX":797.0147705078125,"pointY":117},"width":553,"sublayerTransform":[1,0,0,0,0,1,0,0,0,0,1,0,0,0,0,1],"contentsRect":{"y":0,"x":0,"width":1,"height":1},"opacity":1,"edgeAntialiasingMask":251658240,"height":144,"hidden":false,"anchorPoint":{"pointX":0.5,"pointY":0.5}},"layers":[{"animations":[],"initialState":{"affineTransform":[1,0,0,1,0,0],"masksToBounds":false,"rotation":0,"scale":1,"position":{"pointX":119.4852294921875,"pointY":315},"width":553,"sublayerTransform":[1,0,0,0,0,1,0,0,0,0,1,-0.0005251186870016398,0,0,0,1],"contentsRect":{"y":0,"x":0,"width":1,"height":1},"opacity":1,"edgeAntialiasingMask":251658240,"height":144,"hidden":false,"anchorPoint":{"pointX":0.21606732277068263,"pointY":2.1875}},"layers":[{"animations":[],"layers":[],"texturedRectangle":{"singleTextureOpacity":1,"textXHeight":1.0260416666666667,"textBaseline":1.0625010596381292,"isBackgroundTexture":true,"isVerticalText":false,"textColor":[0,0,0,1],"textureType":6},"initialState":{"affineTransform":[1,0,0,1,0,0],"masksToBounds":false,"rotation":0,"scale":1,"position":{"pointX":304.9852294921875,"pointY":138},"width":553,"sublayerTransform":[1,0,0,0,0,1,0,0,0,0,1,0,0,0,0,1],"contentsRect":{"y":0,"x":0,"width":1,"height":1},"opacity":1,"edgeAntialiasingMask":0,"height":144,"hidden":false,"anchorPoint":{"pointX":0.5,"pointY":0.5}},"texture":"1347933E04244CB1F684C3CBCC629084"}]}]},{"animations":[],"initialState":{"affineTransform":[1,0,0,1,0,0],"masksToBounds":false,"rotation":0,"scale":1,"position":{"pointX":350.5,"pointY":504.152587890625},"width":357,"sublayerTransform":[1,0,0,0,0,1,0,0,0,0,1,0,0,0,0,1],"contentsRect":{"y":0,"x":0,"width":1,"height":1},"opacity":1,"edgeAntialiasingMask":251658240,"height":357,"hidden":false,"anchorPoint":{"pointX":0.5,"pointY":0.5}},"layers":[{"animations":[],"initialState":{"affineTransform":[1,0,0,1,0,0],"masksToBounds":false,"rotation":0,"scale":1,"position":{"pointX":468,"pointY":34.347412109375},"width":357,"sublayerTransform":[1,0,0,0,0,1,0,0,0,0,1,-0.0005251186870016398,0,0,0,1],"contentsRect":{"y":0,"x":0,"width":1,"height":1},"opacity":1,"edgeAntialiasingMask":251658240,"height":357,"hidden":false,"anchorPoint":{"pointX":1.3109243697478992,"pointY":0.096211238401610638}},"layers":[{"animations":[],"layers":[],"texturedRectangle":{"isBackgroundTexture":true,"singleTextureOpacity":1,"textureType":5,"textBaseline":0,"textXHeight":0,"isVerticalText":false},"initialState":{"affineTransform":[1,0,0,1,0,0],"masksToBounds":false,"rotation":0,"scale":1,"position":{"pointX":177.5,"pointY":176.847412109375},"width":357,"sublayerTransform":[1,0,0,0,0,1,0,0,0,0,1,0,0,0,0,1],"contentsRect":{"y":0,"x":0,"width":1,"height":1},"opacity":1,"edgeAntialiasingMask":0,"height":357,"hidden":false,"anchorPoint":{"pointX":0.5,"pointY":0.5}},"texture":"F5118637D28E65DB0CFE82C14CCECE8E"}]}]},{"animations":[],"initialState":{"affineTransform":[1,0,0,1,0,0],"masksToBounds":false,"rotation":0,"scale":1,"position":{"pointX":160.023193359375,"pointY":-61.5},"width":304,"sublayerTransform":[1,0,0,0,0,1,0,0,0,0,1,0,0,0,0,1],"contentsRect":{"y":0,"x":0,"width":1,"height":1},"opacity":1,"edgeAntialiasingMask":251658240,"height":209,"hidden":false,"anchorPoint":{"pointX":0.5,"pointY":0.5}},"layers":[{"animations":[],"initialState":{"affineTransform":[1,0,0,1,0,0],"masksToBounds":false,"rotation":0,"scale":1,"position":{"pointX":631.976806640625,"pointY":526},"width":304,"sublayerTransform":[1,0,0,0,0,1,0,0,0,0,1,-0.0005251186870016398,0,0,0,1],"contentsRect":{"y":0,"x":0,"width":1,"height":1},"opacity":1,"edgeAntialiasingMask":251658240,"height":209,"hidden":false,"anchorPoint":{"pointX":2.0788710744757402,"pointY":2.5167464114832536}},"layers":[{"animations":[],"layers":[],"texturedRectangle":{"singleTextureOpacity":1,"textXHeight":0.99869856459330153,"textBaseline":0.99751332844273322,"isBackgroundTexture":true,"isVerticalText":false,"textColor":[0,0,0,1],"textureType":6},"initialState":{"affineTransform":[1,0,0,1,0,0],"masksToBounds":false,"rotation":0,"scale":1,"position":{"pointX":194.976806640625,"pointY":396.5},"width":304,"sublayerTransform":[1,0,0,0,0,1,0,0,0,0,1,0,0,0,0,1],"contentsRect":{"y":0,"x":0,"width":1,"height":1},"opacity":1,"edgeAntialiasingMask":0,"height":209,"hidden":false,"anchorPoint":{"pointX":0.5,"pointY":0.5}},"texture":"C30918506A3DD362A001CD80A988B4D7"}]}]},{"animations":[],"initialState":{"affineTransform":[1,0,0,1,0,0],"masksToBounds":false,"rotation":0,"scale":1,"position":{"pointX":636.99999934434891,"pointY":690},"width":27,"sublayerTransform":[1,0,0,0,0,1,0,0,0,0,1,0,0,0,0,1],"contentsRect":{"y":0,"x":0,"width":1,"height":1},"opacity":1,"edgeAntialiasingMask":251658240,"height":14,"hidden":false,"anchorPoint":{"pointX":0.5,"pointY":0.5}},"layers":[{"animations":[],"initialState":{"affineTransform":[1,0,0,1,0,0],"masksToBounds":false,"rotation":0,"scale":1,"position":{"pointX":16.500000655651093,"pointY":-323},"width":27,"sublayerTransform":[1,0,0,0,0,1,0,0,0,0,1,-0.0005251186870016398,0,0,0,1],"contentsRect":{"y":0,"x":0,"width":1,"height":1},"opacity":1,"edgeAntialiasingMask":251658240,"height":14,"hidden":false,"anchorPoint":{"pointX":0.61111113539448492,"pointY":-23.071428571428573}},"layers":[{"animations":[],"layers":[],"texturedRectangle":{"singleTextureOpacity":1,"textXHeight":0.5139508928571429,"textBaseline":0.8794642857142857,"isBackgroundTexture":true,"isVerticalText":false,"textColor":[0,0,0,1],"textureType":6},"initialState":{"affineTransform":[1,0,0,1,0,0],"masksToBounds":false,"rotation":0,"scale":1,"position":{"pointX":16.000000655651093,"pointY":14},"width":27,"sublayerTransform":[1,0,0,0,0,1,0,0,0,0,1,0,0,0,0,1],"contentsRect":{"y":0,"x":0,"width":1,"height":1},"opacity":1,"edgeAntialiasingMask":0,"height":14,"hidden":false,"anchorPoint":{"pointX":0.5,"pointY":0.5}},"texture":"5840FDD888AEFE7FEE4D3E821FDD3156"}]}]},{"animations":[],"initialState":{"affineTransform":[1,0,0,1,0,0],"masksToBounds":false,"rotation":0,"scale":1,"position":{"pointX":812.64599609375,"pointY":479.5},"width":345,"sublayerTransform":[1,0,0,0,0,1,0,0,0,0,1,0,0,0,0,1],"contentsRect":{"y":0,"x":0,"width":1,"height":1},"opacity":1,"edgeAntialiasingMask":251658240,"height":211,"hidden":false,"anchorPoint":{"pointX":0.5,"pointY":0.5}},"layers":[{"animations":[],"initialState":{"affineTransform":[1,0,0,1,0,0],"masksToBounds":false,"rotation":0,"scale":1,"position":{"pointX":-0.14599609375,"pointY":-14},"width":345,"sublayerTransform":[1,0,0,0,0,1,0,0,0,0,1,-0.0005251186870016398,0,0,0,1],"contentsRect":{"y":0,"x":0,"width":1,"height":1},"opacity":1,"edgeAntialiasingMask":251658240,"height":211,"hidden":false,"anchorPoint":{"pointX":-0.00042317708333333335,"pointY":-0.066350710900473939}},"layers":[{"animations":[],"layers":[],"texturedRectangle":{"singleTextureOpacity":1,"textXHeight":0.70023696682464454,"textBaseline":0.94786802174355744,"isBackgroundTexture":true,"isVerticalText":false,"textColor":[0,0,0,1],"textureType":6},"initialState":{"affineTransform":[1,0,0,1,0,0],"masksToBounds":false,"rotation":0,"scale":1,"position":{"pointX":227.35400390625,"pointY":124.5},"width":345,"sublayerTransform":[1,0,0,0,0,1,0,0,0,0,1,0,0,0,0,1],"contentsRect":{"y":0,"x":0,"width":1,"height":1},"opacity":1,"edgeAntialiasingMask":0,"height":211,"hidden":false,"anchorPoint":{"pointX":0.5,"pointY":0.5}},"texture":"4A1483485811F20AF8B070A742C121A3"}]}]},{"animations":[],"initialState":{"affineTransform":[1,0,0,1,0,0],"masksToBounds":false,"rotation":0,"scale":1,"position":{"pointX":1470,"pointY":28.5},"width":224,"sublayerTransform":[1,0,0,0,0,1,0,0,0,0,1,0,0,0,0,1],"contentsRect":{"y":0,"x":0,"width":1,"height":1},"opacity":1,"edgeAntialiasingMask":251658240,"height":229,"hidden":false,"anchorPoint":{"pointX":0.5,"pointY":0.5}},"layers":[{"animations":[],"initialState":{"affineTransform":[1,0,0,1,0,0],"masksToBounds":false,"rotation":0,"scale":1,"position":{"pointX":-718,"pointY":446},"width":224,"sublayerTransform":[1,0,0,0,0,1,0,0,0,0,1,-0.0005251186870016398,0,0,0,1],"contentsRect":{"y":0,"x":0,"width":1,"height":1},"opacity":1,"edgeAntialiasingMask":251658240,"height":229,"hidden":false,"anchorPoint":{"pointX":-3.2053571428571428,"pointY":1.9475982532751093}},"layers":[{"animations":[],"layers":[],"texturedRectangle":{"isBackgroundTexture":true,"singleTextureOpacity":1,"textureType":5,"textBaseline":0,"textXHeight":0,"isVerticalText":false},"initialState":{"affineTransform":[1,0,0,1,0,0],"masksToBounds":false,"rotation":0,"scale":1,"position":{"pointX":111,"pointY":113.5},"width":224,"sublayerTransform":[1,0,0,0,0,1,0,0,0,0,1,0,0,0,0,1],"contentsRect":{"y":0,"x":0,"width":1,"height":1},"opacity":1,"edgeAntialiasingMask":0,"height":229,"hidden":false,"anchorPoint":{"pointX":0.5,"pointY":0.5}},"texture":"9B0CE0A95728ED838AEA01C26CB7FA57"}]}]},{"animations":[],"initialState":{"affineTransform":[1,0,0,1,0,0],"masksToBounds":false,"rotation":0,"scale":1,"position":{"pointX":123.023193359375,"pointY":69.5},"width":380,"sublayerTransform":[1,0,0,0,0,1,0,0,0,0,1,0,0,0,0,1],"contentsRect":{"y":0,"x":0,"width":1,"height":1},"opacity":1,"edgeAntialiasingMask":251658240,"height":209,"hidden":false,"anchorPoint":{"pointX":0.5,"pointY":0.5}},"layers":[{"animations":[],"initialState":{"affineTransform":[1,0,0,1,0,0],"masksToBounds":false,"rotation":0,"scale":1,"position":{"pointX":706.976806640625,"pointY":395},"width":380,"sublayerTransform":[1,0,0,0,0,1,0,0,0,0,1,-0.0005251186870016398,0,0,0,1],"contentsRect":{"y":0,"x":0,"width":1,"height":1},"opacity":1,"edgeAntialiasingMask":251658240,"height":209,"hidden":false,"anchorPoint":{"pointX":1.8604652806332236,"pointY":1.8899521531100478}},"layers":[{"animations":[],"layers":[],"texturedRectangle":{"singleTextureOpacity":1,"textXHeight":0.74688995215311005,"textBaseline":0.99521633312462621,"isBackgroundTexture":true,"isVerticalText":false,"textColor":[0,0,0,1],"textureType":6},"initialState":{"affineTransform":[1,0,0,1,0,0],"masksToBounds":false,"rotation":0,"scale":1,"position":{"pointX":206.976806640625,"pointY":271.5},"width":380,"sublayerTransform":[1,0,0,0,0,1,0,0,0,0,1,0,0,0,0,1],"contentsRect":{"y":0,"x":0,"width":1,"height":1},"opacity":1,"edgeAntialiasingMask":0,"height":209,"hidden":true,"anchorPoint":{"pointX":0.5,"pointY":0.5}},"texture":"A8288665C890835D50CBD17E8C8FEB9D"}]}]},{"animations":[],"initialState":{"affineTransform":[1,0,0,1,0,0],"masksToBounds":false,"rotation":0,"scale":1,"position":{"pointX":636.99999934434891,"pointY":690},"width":27,"sublayerTransform":[1,0,0,0,0,1,0,0,0,0,1,0,0,0,0,1],"contentsRect":{"y":0,"x":0,"width":1,"height":1},"opacity":1,"edgeAntialiasingMask":251658240,"height":14,"hidden":false,"anchorPoint":{"pointX":0.5,"pointY":0.5}},"layers":[{"animations":[],"initialState":{"affineTransform":[1,0,0,1,0,0],"masksToBounds":false,"rotation":0,"scale":1,"position":{"pointX":16.500000655651093,"pointY":-323},"width":27,"sublayerTransform":[1,0,0,0,0,1,0,0,0,0,1,-0.0005251186870016398,0,0,0,1],"contentsRect":{"y":0,"x":0,"width":1,"height":1},"opacity":1,"edgeAntialiasingMask":251658240,"height":14,"hidden":false,"anchorPoint":{"pointX":0.61111113539448492,"pointY":-23.071428571428573}},"layers":[{"animations":[],"layers":[],"texturedRectangle":{"singleTextureOpacity":1,"textXHeight":0.5139508928571429,"textBaseline":0.8794642857142857,"isBackgroundTexture":true,"isVerticalText":false,"textColor":[0,0,0,1],"textureType":6},"initialState":{"affineTransform":[1,0,0,1,0,0],"masksToBounds":false,"rotation":0,"scale":1,"position":{"pointX":16.000000655651093,"pointY":14},"width":27,"sublayerTransform":[1,0,0,0,0,1,0,0,0,0,1,0,0,0,0,1],"contentsRect":{"y":0,"x":0,"width":1,"height":1},"opacity":1,"edgeAntialiasingMask":0,"height":14,"hidden":true,"anchorPoint":{"pointX":0.5,"pointY":0.5}},"texture":"2CACF84A11B392050CFF2F099D092F82"}]}]},{"animations":[],"initialState":{"affineTransform":[1,0,0,1,0,0],"masksToBounds":false,"rotation":0,"scale":1,"position":{"pointX":1470,"pointY":28.5},"width":224,"sublayerTransform":[1,0,0,0,0,1,0,0,0,0,1,0,0,0,0,1],"contentsRect":{"y":0,"x":0,"width":1,"height":1},"opacity":1,"edgeAntialiasingMask":251658240,"height":229,"hidden":false,"anchorPoint":{"pointX":0.5,"pointY":0.5}},"layers":[{"animations":[],"initialState":{"affineTransform":[1,0,0,1,0,0],"masksToBounds":false,"rotation":0,"scale":1,"position":{"pointX":-718,"pointY":446},"width":224,"sublayerTransform":[1,0,0,0,0,1,0,0,0,0,1,-0.0005251186870016398,0,0,0,1],"contentsRect":{"y":0,"x":0,"width":1,"height":1},"opacity":1,"edgeAntialiasingMask":251658240,"height":229,"hidden":false,"anchorPoint":{"pointX":-3.2053571428571428,"pointY":1.9475982532751093}},"layers":[{"animations":[],"layers":[],"texturedRectangle":{"isBackgroundTexture":true,"singleTextureOpacity":1,"textureType":5,"textBaseline":0,"textXHeight":0,"isVerticalText":false},"initialState":{"affineTransform":[1,0,0,1,0,0],"masksToBounds":false,"rotation":0,"scale":1,"position":{"pointX":111,"pointY":113.5},"width":224,"sublayerTransform":[1,0,0,0,0,1,0,0,0,0,1,0,0,0,0,1],"contentsRect":{"y":0,"x":0,"width":1,"height":1},"opacity":1,"edgeAntialiasingMask":0,"height":229,"hidden":true,"anchorPoint":{"pointX":0.5,"pointY":0.5}},"texture":"453908F53C17B73A863A51D614A958E3"}]}]}]}}]}